swannotifications/__init__.py
swannotifications/_version.py
swannotifications/labextension/swan-cern-swannotifications-1.0.0.tgz
swannotifications/nbextension/extension.js
swannotifications-1.0.0.data/data/share/jupyter/lab/extensions/swan-cern-swannotifications-1.0.0.tgz
swannotifications-1.0.0.dist-info/METADATA
swannotifications-1.0.0.dist-info/WHEEL
swannotifications-1.0.0.dist-info/top_level.txt
swannotifications-1.0.0.dist-info/RECORD
